<?xml version="1.0" encoding="utf-8"?>
<myopenmath xmlns:pi="http://pretextbook.org/2020/pretext/internal" id="1064915">
<statement>
<p>It is estimated that 57.9<percent/> of Kickstarter projects are successfully funded. Assume each Kickstarter project is independent. A random sample of 17 Kickstarter projects are followed. Let <m>\displaystyle{X}</m> be the number Kickstarter projects that are successfully funded. Calculate the following:</p>
<p>a. <m>\displaystyle\mu_{{X}}</m>: <fillin characters="4" /></p>
<p>b. <m>\displaystyle\sigma_{{X}}</m>: <fillin characters="4" /></p>
<p>c. <m>\displaystyle{P}{\left({X}={9}\right)}</m>: <fillin characters="4" /></p>
<p>d. <m>\displaystyle{P}{\left({X}{<}{11}\right)}</m>: <fillin characters="4" /></p>
<p>e. <m>\displaystyle{P}{\left({X}{>}{8}\right)}</m>: <fillin characters="4" /></p>
<p>f.  <m>\displaystyle{P}{\left({X}\geq{8}\right)}</m>: <fillin characters="4" /></p>
<p>g. <m>\displaystyle{P}{\left({8}\leq{X}\leq{11}\right)}</m>: <fillin characters="20" /></p>

</statement>
<solution>
<p><ul><li>9.843</li><li>2.0356578789178</li><li>0.1754481523776</li><li>0.62141253087301</li><li>0.74707026536906</li><li>0.8746413723955</li><li>0.66499568756201</li></ul></p>
</solution>
</myopenmath>

